bdtool/__about__.py
bdtool/__init__.py
bdtool/rule.py
bdtool/share.py
bdtool/string.py
bdtool/tool.py
bdtool/docxext/__init__.py
bdtool/docxext/executer.py
bdtool/docxext/math.py
bdtool/docxext/util.py
bdtool/docxext/oxml/__init__.py
bdtool/docxext/oxml/parse_word_xml.py
bdtool/docxext/oxml/set_rpr.py
bdtool/docxext/oxml/math/__init__.py
bdtool/docxext/oxml/math/block.py
bdtool/docxext/oxml/math/math.py
bdtool/docxext/oxml/math/nary.py
bdtool/docxext/oxml/math/run.py
bdtool/docxext/oxml/math/share.py
bdtool/docxext/oxml/math/subsup.py
bdtool/docxext/oxml/math/sup.py
bdtool/workflow/io_type.py
python_bdtool-0.0.1004.dist-info/METADATA
python_bdtool-0.0.1004.dist-info/WHEEL
python_bdtool-0.0.1004.dist-info/entry_points.txt
python_bdtool-0.0.1004.dist-info/licenses/LICENSE
python_bdtool-0.0.1004.dist-info/RECORD
