Metadata-Version: 2.4
Name: python-bdtool
Version: 0.0.1004
Summary: Some python tools for bioinformatics-development
Project-URL: Documentation, https://github.com/hs3434/python-bdtool#readme
Project-URL: Issues, https://github.com/hs3434/python-bdtool/issues
Project-URL: Source, https://github.com/hs3434/python-bdtool
Author-email: husheng <hs3434.work@gmail.com>
License-Expression: MIT
License-File: LICENSE
Classifier: Development Status :: 2 - Pre-Alpha
Classifier: Programming Language :: Python
Classifier: Programming Language :: Python :: 3.10
Classifier: Programming Language :: Python :: 3.11
Classifier: Programming Language :: Python :: 3.12
Classifier: Programming Language :: Python :: Implementation :: CPython
Classifier: Programming Language :: Python :: Implementation :: PyPy
Requires-Python: >=3.10
Requires-Dist: snakemake>=8.13.0
